<?xml version="1.0" encoding="UTF-8" standalone="yes"?>
<view title="admin.importExport.edit.title" name="_selectMode"
	xsi:schemaLocation="http://www.skyve.org/xml/view ../../../../schemas/view.xsd"
	xmlns="http://www.skyve.org/xml/view"
	xmlns:c="http://www.skyve.org/xml/common"
	xmlns:xsi="http://www.w3.org/2001/XMLSchema-instance">
	<vbox border="true"
		borderTitle="admin.importExport.selectMode.borderTitle">
		<form>
			<column responsiveWidth="2" />
			<column />
			<column />
			<row>
				<item>
					<radio binding="mode" vertical="false">
						<onChangedHandlers>
							<rerender clientValidation="false" />
						</onChangedHandlers>
					</radio>
				</item>
				<item>
					<button pixelWidth="250" action="GetImportTemplate" />
				</item>
			</row>
		</form>
	</vbox>
</view>
